ishakscraping.py
ishakscraping-0.0.1.dist-info/LICENSE.txt
ishakscraping-0.0.1.dist-info/METADATA
ishakscraping-0.0.1.dist-info/WHEEL
ishakscraping-0.0.1.dist-info/top_level.txt
ishakscraping-0.0.1.dist-info/RECORD
